{"cameraMode":{"drawMode":0,"name":"Shaded","section":"Shading Mode"},"sceneLighting":true,"audioPlay":false,"sceneViewState":{"m_AlwaysRefresh":false,"showFog":true,"showSkybox":true,"showFlares":true,"showImageEffects":true,"showParticleSystems":true,"showVisualEffectGraphs":true,"m_FxEnabled":true},"in2DMode":false,"pivot":{"x":0.3978154957294464,"y":-0.7086171507835388,"z":1.9336118698120118},"rotation":{"x":0.15200869739055634,"y":0.09640941023826599,"z":-0.014930098317563534,"w":0.9838144779205322},"size":1.8556461334228516,"orthographic":false}